README.md
setup.py
py_temp/__init__.py
py_temp/cli.py
py_temp/conffile.py
py_temp/manifest.py
py_temp/run.py
py_temp/select.py
py_temp.egg-info/PKG-INFO
py_temp.egg-info/SOURCES.txt
py_temp.egg-info/dependency_links.txt
py_temp.egg-info/entry_points.txt
py_temp.egg-info/requires.txt
py_temp.egg-info/top_level.txt