Metadata-Version: 2.1
Name: py-temp
Version: 0.0.4
Summary: A CLI tool for rendering python code using Jinja2.
Home-page: https://github.com/TeamNightSky/PyTemp
Author: FoxNerdSaysMoo, GrandMoff100
Author-email: teamnightsky.gh@gmail.com
License: UNKNOWN
Platform: UNKNOWN
